{
  "socials": [
    {
      "socialName": "YouTube",
      "socialDescription": "Official HEAT Labs YouTube Channel",
      "socialURL": "https://www.youtube.com/@HEATLabs-Official"
    },
	{
      "socialName": "GitHub",
      "socialDescription": "Official HEAT Labs GitHub Organization",
      "socialURL": "https://github.com/HEATLabs"
    },
	{
      "socialName": "Twitter",
      "socialDescription": "Official HEAT Labs Twitter Account",
      "socialURL": "https://x.com/HEAT_Labs"
    },
	{
      "socialName": "Nexus Mods",
      "socialDescription": "Official HEAT Labs Nexus Mods Profile",
      "socialURL": "https://next.nexusmods.com/profile/HEATLabs"
    },
	{
      "socialName": "Discord",
      "socialDescription": "Official HEAT Labs Discord Server",
      "socialURL": "https://discord.com/invite/caEFCA9ScF"
    }
  ]
}